{
	"configurations" : 
	[
		{
			"directories" : 
			[
				{
					"build" : ".",
					"jsonFile" : "directory-.-Debug-d0094a50bb2071803777.json",
					"minimumCMakeVersion" : 
					{
						"string" : "3.22"
					},
					"projectIndex" : 0,
					"source" : ".",
					"targetIndexes" : 
					[
						0
					]
				}
			],
			"name" : "Debug",
			"projects" : 
			[
				{
					"directoryIndexes" : 
					[
						0
					],
					"name" : "if_else_if",
					"targetIndexes" : 
					[
						0
					]
				}
			],
			"targets" : 
			[
				{
					"directoryIndex" : 0,
					"id" : "if_else_if::@6890427a1f51a3e7e1df",
					"jsonFile" : "target-if_else_if-Debug-b721f13c6be5438d8b19.json",
					"name" : "if_else_if",
					"projectIndex" : 0
				}
			]
		}
	],
	"kind" : "codemodel",
	"paths" : 
	{
		"build" : "C:/Users/Molham Team/Desktop/--C--/C-tutorial/if-else-if/cmake-build-debug",
		"source" : "C:/Users/Molham Team/Desktop/--C--/C-tutorial/if-else-if"
	},
	"version" : 
	{
		"major" : 2,
		"minor" : 3
	}
}
